{
  "name": "json",
  "version": "1.0.0",
  "description": "",
  "main": "index.js",
  "scripts": {
    "test": "echo \"Error: no test specified\" && exit 1"
  },
  "repository": {
    "type": "git",
    "url": "https://github.com/Gab-San/ing-sw-2024-Panceri-Ruzza-Santandrea-Villa.git"
  },
  "private": true,
  "goldCard" : [
    {
      "cardId": "G0",
      "placementCost": [
        {"type": "MUSHROOM", "amount" : 2},
        {"type": "WOLF", "amount": 1}
      ],
      "pointsOnPlace": [
        {"type": "QUILL", "amount" : 1}
      ],
      "cornersJ": [
        {"direction": "TL", "frontResource": "FILLED", "backResource": "NULL"},
        {"direction": "TR", "frontResource": "NULL", "backResource": "NULL"},
        {"direction": "BL", "frontResource": "NULL", "backResource": "NULL"},
        {"direction": "BR", "frontResource": "QUILL", "backResource": "NULL"}
      ],
      "backResource": "MUSHROOM",
      "frontImageFileName": "img_G0_front.jpg",
      "backImageFileName": "img_G0_back.jpg"
    },
    {
      "cardId": "G1",
      "placementCost": [
        {"type":"MUSHROOM", "amount": 2},
        {"type":"LEAF", "amount": 1}
      ],
      "pointsOnPlace": [
        {"type": "POTION", "amount":  1}
      ],
      "cornersJ": [
        {"direction": "TL", "frontResource": "NULL", "backResource": "NULL"},
        {"direction": "TR", "frontResource": "POTION", "backResource": "NULL"},
        {"direction": "BL", "frontResource": "FILLED", "backResource": "NULL"},
        {"direction": "BR", "frontResource": "NULL", "backResource": "NULL"}
      ],
      "backResource": "MUSHROOM",
      "frontImageFileName": "img_G1_front.jpg",
      "backImageFileName": "img_G0_back.jpg"
    },
    {
      "cardId": "G2",
      "placementCost": [
        {"type":"MUSHROOM", "amount": 2},
        {"type":"BUTTERFLY", "amount": 1}
      ],
      "pointsOnPlace": [
        {"type":"SCROLL", "amount":  1}
      ],
      "cornersJ": [
        {"direction": "TL", "frontResource": "SCROLL", "backResource": "NULL"},
        {"direction": "TR", "frontResource": "NULL", "backResource": "NULL"},
        {"direction": "BL", "frontResource": "NULL", "backResource": "NULL"},
        {"direction": "BR", "frontResource": "FILLED", "backResource": "NULL"}
      ],
      "backResource": "MUSHROOM",
      "frontImageFileName": "img_G2_front.jpg",
      "backImageFileName": "img_G0_back.jpg"
    },
    {
      "cardId": "G3",
      "placementCost": [
        {"type":"MUSHROOM","amount": 3},
        {"type":"WOLF", "amount" :1}
      ],
      "pointsOnPlace": [
        {"type": "CORNERCOVER", "amount": 2}
      ],
      "cornersJ": [
        {"direction": "TL", "frontResource": "NULL", "backResource": "NULL"},
        {"direction": "TR", "frontResource": "NULL", "backResource": "NULL"},
        {"direction": "BL", "frontResource": "FILLED", "backResource": "NULL"},
        {"direction": "BR", "frontResource": "NULL", "backResource": "NULL"}
      ],
      "backResource": "MUSHROOM",
      "frontImageFileName": "img_G3_front.jpg",
      "backImageFileName": "img_G0_back.jpg"
    },
    {
      "cardId": "G4",
      "placementCost": [
        {"type":"MUSHROOM", "amount": 3},
        {"type":"LEAF", "amount": 1}
      ],
      "pointsOnPlace": [
        {"type": "CORNERCOVER", "amount": 2}
      ],
      "cornersJ": [
        {"direction": "TL", "frontResource": "NULL", "backResource": "NULL"},
        {"direction": "TR", "frontResource": "NULL", "backResource": "NULL"},
        {"direction": "BL", "frontResource": "NULL", "backResource": "NULL"},
        {"direction": "BR", "frontResource": "FILLED", "backResource": "NULL"}
      ],
      "backResource": "MUSHROOM",
      "frontImageFileName": "img_G4_front.jpg",
      "backImageFileName": "img_G0_back.jpg"
    },
    {
      "cardId": "G5",
      "placementCost": [
        {"type":"MUSHROOM","amount": 3},
        {"type":"BUTTERFLY", "amount" : 1}
      ],
      "pointsOnPlace": [
        {"type": "CORNERCOVER", "amount": 2}
      ],
      "cornersJ": [
        {"direction": "TL", "frontResource": "NULL", "backResource": "NULL"},
        {"direction": "TR", "frontResource": "FILLED", "backResource": "NULL"},
        {"direction": "BL", "frontResource": "NULL", "backResource": "NULL"},
        {"direction": "BR", "frontResource": "NULL", "backResource": "NULL"}
      ],
      "backResource": "MUSHROOM",
      "frontImageFileName": "img_G5_front.jpg",
      "backImageFileName": "img_G0_back.jpg"
    },
    {
      "cardId": "G6",
      "placementCost": [
        {"type":"MUSHROOM","amount": 3}
      ],
      "pointsOnPlace": [
        {"type": "SIMPLEPOINT", "amount":3}
      ],
      "cornersJ": [
        {"direction": "TL", "frontResource": "NULL", "backResource": "NULL"},
        {"direction": "TR", "frontResource": "FILLED", "backResource": "NULL"},
        {"direction": "BL", "frontResource": "POTION", "backResource": "NULL"},
        {"direction": "BR", "frontResource": "FILLED", "backResource": "NULL"}
      ],
      "backResource": "MUSHROOM",
      "frontImageFileName": "img_G6_front.jpg",
      "backImageFileName": "img_G0_back.jpg"
    },
    {
      "cardId": "G7",
      "placementCost": [
        {"type":"MUSHROOM", "amount":3}
      ],
      "pointsOnPlace": [
        {"type": "SIMPLEPOINT","amount":3}
      ],
      "cornersJ": [
        {"direction": "TL", "frontResource": "QUILL", "backResource": "NULL"},
        {"direction": "TR", "frontResource": "NULL", "backResource": "NULL"},
        {"direction": "BL", "frontResource": "FILLED", "backResource": "NULL"},
        {"direction": "BR", "frontResource": "FILLED", "backResource": "NULL"}
      ],
      "backResource": "MUSHROOM",
      "frontImageFileName": "img_G7_front.jpg",
      "backImageFileName": "img_G0_back.jpg"
    },
    {
      "cardId": "G8",
      "placementCost": [
        {"type":"MUSHROOM","amount":3}
      ],
      "pointsOnPlace": [
        {"type": "SIMPLEPOINT", "amount":3}
      ],
      "cornersJ": [
        {"direction": "TL", "frontResource": "FILLED", "backResource": "NULL"},
        {"direction": "TR", "frontResource": "SCROLL", "backResource": "NULL"},
        {"direction": "BL", "frontResource": "FILLED", "backResource": "NULL"},
        {"direction": "BR", "frontResource": "NULL", "backResource": "NULL"}
      ],
      "backResource": "MUSHROOM",
      "frontImageFileName": "img_G8_front.jpg",
      "backImageFileName": "img_G0_back.jpg"
    },
    {
      "type": "GoldCard",
      "cardId": "G9",
      "pointsOnPlace": [
        {"type": "SIMPLEPOINT", "amount":5}
      ],
      "placementCost": [
        {"type": "MUSHROOM", "amount":5}
      ],
      "cornersJ": [
        {"direction": "TL", "frontResource": "NULL", "backResource": "NULL"},
        {"direction": "TR", "frontResource": "FILLED", "backResource": "NULL"},
        {"direction": "BL", "frontResource": "NULL", "backResource": "NULL"},
        {"direction": "BR", "frontResource": "FILLED", "backResource": "NULL"}
      ],
      "backResource": "MUSHROOM",
      "frontImageFileName": "img_G9_front.jpg",
      "backImageFileName": "img_G0_back.jpg"
    },
    {
      "cardId": "G10",
      "pointsOnPlace": [
        {"type":"QUILL", "amount": 1}
      ],
      "placementCost": [
        {"type": "LEAF", "amount": 2},
        {"type": "BUTTERFLY", "amount":  1}
      ],
      "cornersJ": [
        {"direction": "TL", "frontResource": "QUILL", "backResource": "NULL"},
        {"direction": "TR", "frontResource": "NULL", "backResource": "NULL"},
        {"direction": "BL", "frontResource": "NULL", "backResource": "NULL"},
        {"direction": "BR", "frontResource": "FILLED", "backResource": "NULL"}
      ],
      "backResource": "LEAF",
      "frontImageFileName": "img_G10_front.jpg",
      "backImageFileName": "img_G10_back.jpg"
    },
    {
      "cardId": "G11",
      "pointsOnPlace": [
        {"type": "SCROLL", "amount":  1}
      ],
      "placementCost": [
        {"type": "LEAF", "amount": 2},
        {"type": "MUSHROOM", "amount":  1}
      ],
      "cornersJ": [
        {"direction": "TL", "frontResource": "NULL", "backResource": "NULL"},
        {"direction": "TR", "frontResource": "SCROLL", "backResource": "NULL"},
        {"direction": "BL", "frontResource": "FILLED", "backResource": "NULL"},
        {"direction": "BR", "frontResource": "NULL", "backResource": "NULL"}
      ],
      "backResource": "LEAF",
      "frontImageFileName": "img_G11_front.jpg",
      "backImageFileName": "img_G10_back.jpg"
    },
    {
      "cardId": "G12",
      "pointsOnPlace": [
        {"type": "POTION", "amount":  1}
      ],
      "placementCost": [
        {"type": "LEAF", "amount": 2},
        {"type": "WOLF", "amount":  1}
      ],
      "cornersJ": [
        {"direction": "TL", "frontResource": "NULL", "backResource": "NULL"},
        {"direction": "TR", "frontResource": "FILLED", "backResource": "NULL"},
        {"direction": "BL", "frontResource": "POTION", "backResource": "NULL"},
        {"direction": "BR", "frontResource": "NULL", "backResource": "NULL"}
      ],
      "backResource": "LEAF",
      "frontImageFileName": "img_G12_front.jpg",
      "backImageFileName": "img_G10_back.jpg"
    },
    {
      "cardId": "G13",
      "placementCost": [
        {"type": "LEAF", "amount": 3},
        {"type" : "BUTTERFLY", "amount" : 1}
      ],
      "pointsOnPlace": [
        {"type":"CORNERCOVER", "amount": 2}
      ],
      "cornersJ": [
        {"direction": "TL", "frontResource": "NULL", "backResource": "NULL"},
        {"direction": "TR", "frontResource": "NULL", "backResource": "NULL"},
        {"direction": "BL", "frontResource": "NULL", "backResource": "NULL"},
        {"direction": "BR", "frontResource": "NULL", "backResource": "NULL"}
      ],
      "backResource": "LEAF",
      "frontImageFileName": "img_G13_front.jpg",
      "backImageFileName": "img_G10_back.jpg"
    },
    {
      "type": "GoldCard",
      "cardId": "G14",
      "pointsOnPlace": [
        {"type": "CORNERCOVER", "amount": 2}
      ],
      "placementCost": [
        {"type": "LEAF", "amount": 3},
        {"type": "WOLF", "amount":  1}
      ],
      "cornersJ": [
        {"direction": "TL", "frontResource": "NULL", "backResource": "NULL"},
        {"direction": "TR", "frontResource": "NULL", "backResource": "NULL"},
        {"direction": "BL", "frontResource": "NULL", "backResource": "NULL"},
        {"direction": "BR", "frontResource": "FILLED", "backResource": "NULL"}
      ],
      "backResource": "LEAF",
      "frontImageFileName": "img_G14_front.jpg",
      "backImageFileName": "img_G10_back.jpg"
    },
    {
      "cardId": "G15",
      "pointsOnPlace": [
        {"type": "CORNERCOVER", "amount": 2}
      ],
      "placementCost": [
        {"type": "LEAF", "amount": 3},
        {"type": "MUSHROOM", "amount":  1}
      ],
      "cornersJ": [
        {"direction": "TL", "frontResource": "NULL", "backResource": "NULL"},
        {"direction": "TR", "frontResource": "FILLED", "backResource": "NULL"},
        {"direction": "BL", "frontResource": "NULL", "backResource": "NULL"},
        {"direction": "BR", "frontResource": "NULL", "backResource": "NULL"}
      ],
      "backResource": "LEAF",
      "frontImageFileName": "img_G15_front.jpg",
      "backImageFileName": "img_G10_back.jpg"
    },
    {
      "cardId": "G16",
      "pointsOnPlace": [
        {"type":  "SIMPLEPOINT", "amount":  3}
      ],
      "placementCost": [
        {"type": "LEAF", "amount": 3}
      ],
      "cornersJ": [
        {"direction": "TL", "frontResource": "NULL", "backResource": "NULL"},
        {"direction": "TR", "frontResource": "FILLED", "backResource": "NULL"},
        {"direction": "BL", "frontResource": "QUILL", "backResource": "NULL"},
        {"direction": "BR", "frontResource": "FILLED", "backResource": "NULL"}
      ],
      "backResource": "LEAF",
      "frontImageFileName": "img_G16_front.jpg",
      "backImageFileName": "img_G10_back.jpg"
    },
    {
      "cardId": "G17",
      "pointsOnPlace":[
        {"type":  "SIMPLEPOINT", "amount":  3}
      ],
      "placementCost": [
        {"type": "LEAF", "amount": 3}
      ],
      "cornersJ": [
        {"direction": "TL", "frontResource": "SCROLL", "backResource": "NULL"},
        {"direction": "TR", "frontResource": "NULL", "backResource": "NULL"},
        {"direction": "BL", "frontResource": "FILLED", "backResource": "NULL"},
        {"direction": "BR", "frontResource": "FILLED", "backResource": "NULL"}
      ],
      "backResource": "LEAF",
      "frontImageFileName": "img_G17_front.jpg",
      "backImageFileName": "img_G10_back.jpg"
    },
    {
      "cardId": "G18",
      "pointsOnPlace":[
        {"type":  "SIMPLEPOINT", "amount":  3}
      ],
      "placementCost": [
        {"type": "LEAF", "amount": 2}
      ],
      "cornersJ": [
        {"direction": "TL", "frontResource": "FILLED", "backResource": "NULL"},
        {"direction": "TR", "frontResource": "POTION", "backResource": "NULL"},
        {"direction": "BL", "frontResource": "FILLED", "backResource": "NULL"},
        {"direction": "BR", "frontResource": "NULL", "backResource": "NULL"}
      ],
      "backResource": "LEAF",
      "frontImageFileName": "img_G18_front.jpg",
      "backImageFileName": "img_G10_back.jpg"
    },
    {
      "cardId": "G19",
      "pointsOnPlace":[
        {"type":  "SIMPLEPOINT", "amount":  5}
      ],
      "placementCost": [
        {"type": "LEAF", "amount": 5}
      ],
      "cornersJ": [
        {"direction": "TL", "frontResource": "NULL", "backResource": "NULL"},
        {"direction": "TR", "frontResource": "NULL", "backResource": "NULL"},
        {"direction": "BL", "frontResource": "FILLED", "backResource": "NULL"},
        {"direction": "BR", "frontResource": "FILLED", "backResource": "NULL"}
      ],
      "backResource": "LEAF",
      "frontImageFileName": "img_G19_front.jpg",
      "backImageFileName": "img_G10_back.jpg"
    },
    {
      "cardId": "G20",
      "pointsOnPlace": [
        {"type": "POTION", "amount": 1}
      ],
      "placementCost": [
        {"type": "WOLF", "amount": 2},
        {"type": "BUTTERFLY", "amount": 1}
      ],
      "cornersJ": [
        {"direction": "TL", "frontResource": "POTION", "backResource": "NULL"},
        {"direction": "TR", "frontResource": "NULL", "backResource": "NULL"},
        {"direction": "BL", "frontResource": "NULL", "backResource": "NULL"},
        {"direction": "BR", "frontResource": "FILLED", "backResource": "NULL"}
      ],
      "backResource": "WOLF",
      "frontImageFileName": "img_G20_front.jpg",
      "backImageFileName": "img_G20_back.jpg"
    },
    {
      "cardId": "G21",
      "pointsOnPlace":[
        {"type": "SCROLL", "amount": 1}
      ],
      "placementCost": [
        {"type": "WOLF", "amount": 2},
        {"type": "LEAF", "amount":  1}
      ],
      "cornersJ": [
        {"direction": "TL", "frontResource": "FILLED", "backResource": "NULL"},
        {"direction": "TR", "frontResource": "NULL", "backResource": "NULL"},
        {"direction": "BL", "frontResource": "NULL", "backResource": "NULL"},
        {"direction": "BR", "frontResource": "SCROLL", "backResource": "NULL"}
      ],
      "backResource": "WOLF",
      "frontImageFileName": "img_G21_front.jpg",
      "backImageFileName": "img_G20_back.jpg"
    },
    {
      "cardId": "G22",
      "pointsOnPlace": [
        {"type": "QUILL", "amount": 1}
      ],
      "placementCost": [
        {"type": "WOLF", "amount": 2},
        {"type": "MUSHROOM", "amount": 1}
      ],
      "cornersJ": [
        {"direction": "TL", "frontResource": "NULL", "backResource": "NULL"},
        {"direction": "TR", "frontResource": "FILLED", "backResource": "NULL"},
        {"direction": "BL", "frontResource": "QUILL", "backResource": "NULL"},
        {"direction": "BR", "frontResource": "NULL", "backResource": "NULL"}
      ],
      "backResource": "WOLF",
      "frontImageFileName": "img_G22_front.jpg",
      "backImageFileName": "img_G20_back.jpg"
    },
    {
      "cardId": "G23",
      "pointsOnPlace": [
        {"type": "CORNERCOVER", "amount": 2}
      ],
      "placementCost": [
        {"type": "WOLF", "amount": 3},
        {"type": "BUTTERFLY", "amount":  1}
      ],
      "cornersJ": [
        {"direction": "TL", "frontResource": "NULL", "backResource": "NULL"},
        {"direction": "TR", "frontResource": "NULL", "backResource": "NULL"},
        {"direction": "BL", "frontResource": "FILLED", "backResource": "NULL"},
        {"direction": "BR", "frontResource": "NULL", "backResource": "NULL"}
      ],
      "backResource": "WOLF",
      "frontImageFileName": "img_G23_front.jpg",
      "backImageFileName": "img_G20_back.jpg"
    },
    {
      "cardId": "G24",
      "pointsOnPlace": [
        {"type": "CORNERCOVER", "amount": 2}
      ],
      "placementCost": [
        {"type": "WOLF", "amount": 3},
        {"type": "MUSHROOM", "amount": 1}
      ],
      "cornersJ": [
        {"direction": "TL", "frontResource": "NULL", "backResource": "NULL"},
        {"direction": "TR", "frontResource": "FILLED", "backResource": "NULL"},
        {"direction": "BL", "frontResource": "NULL", "backResource": "NULL"},
        {"direction": "BR", "frontResource": "NULL", "backResource": "NULL"}
      ],
      "backResource": "WOLF",
      "frontImageFileName": "img_G24_front.jpg",
      "backImageFileName": "img_G20_back.jpg"
    },
    {
      "cardId": "G25",
      "pointsOnPlace": [
        {"type": "CORNERCOVER", "amount": 2}
      ],
      "placementCost": [
        {"type": "WOLF", "amount": 3},
        {"type": "LEAF", "amount":  1}
      ],
      "cornersJ": [
        {"direction": "TL", "frontResource": "FILLED", "backResource": "NULL"},
        {"direction": "TR", "frontResource": "NULL", "backResource": "NULL"},
        {"direction": "BL", "frontResource": "NULL", "backResource": "NULL"},
        {"direction": "BR", "frontResource": "NULL", "backResource": "NULL"}
      ],
      "backResource": "WOLF",
      "frontImageFileName": "img_G25_front.jpg",
      "backImageFileName": "img_G20_back.jpg"
    },
    {
      "cardId": "G26",
      "pointsOnPlace":  [
        {"type":  "SIMPLEPOINT", "amount":  3}
      ],
      "placementCost": [
        {"type": "WOLF", "amount": 3}
      ],
      "cornersJ": [
        {"direction": "TL", "frontResource": "NULL", "backResource": "NULL"},
        {"direction": "TR", "frontResource": "FILLED", "backResource": "NULL"},
        {"direction": "BL", "frontResource": "SCROLL", "backResource": "NULL"},
        {"direction": "BR", "frontResource": "FILLED", "backResource": "NULL"}
      ],
      "backResource": "WOLF",
      "frontImageFileName": "img_G26_front.jpg",
      "backImageFileName": "img_G20_back.jpg"
    },
    {
      "cardId": "G27",
      "pointsOnPlace": [
        {"type":  "SIMPLEPOINT", "amount":  3}
      ],
      "placementCost": [
        {"type": "WOLF", "amount": 3}
      ],
      "cornersJ": [
        {"direction": "TL", "frontResource": "NULL", "backResource": "NULL"},
        {"direction": "TR", "frontResource": "POTION", "backResource": "NULL"},
        {"direction": "BL", "frontResource": "FILLED", "backResource": "NULL"},
        {"direction": "BR", "frontResource": "FILLED", "backResource": "NULL"}
      ],
      "backResource": "WOLF",
      "frontImageFileName": "img_G27_front.jpg",
      "backImageFileName": "img_G20_back.jpg"
    },
    {
      "cardId": "G28",
      "pointsOnPlace": [
        {"type":  "SIMPLEPOINT", "amount":  3}
      ],
      "placementCost": [
        {"type": "WOLF", "amount": 3}
      ],
      "cornersJ": [
        {"direction": "TL", "frontResource": "FILLED", "backResource": "NULL"},
        {"direction": "TR", "frontResource": "NULL", "backResource": "NULL"},
        {"direction": "BL", "frontResource": "FILLED", "backResource": "NULL"},
        {"direction": "BR", "frontResource": "QUILL", "backResource": "NULL"}
      ],
      "backResource": "WOLF",
      "frontImageFileName": "img_G28_front.jpg",
      "backImageFileName": "img_G20_back.jpg"
    },
    {
      "cardId": "G29",
      "pointsOnPlace": [
        {"type":  "SIMPLEPOINT", "amount":  5}
      ],
      "placementCost": [
        {"type": "WOLF", "amount": 5}
      ],
      "cornersJ": [
        {"direction": "TL", "frontResource": "FILLED", "backResource": "NULL"},
        {"direction": "TR", "frontResource": "NULL", "backResource": "NULL"},
        {"direction": "BL", "frontResource": "FILLED", "backResource": "NULL"},
        {"direction": "BR", "frontResource": "NULL", "backResource": "NULL"}
      ],
      "backResource": "WOLF",
      "frontImageFileName": "img_G29_front.jpg",
      "backImageFileName": "img_G20_back.jpg"
    },
    {
      "cardId": "G30",
      "pointsOnPlace": [
        {"type": "QUILL", "amoumnt": 1}
      ],
      "placementCost": [
        {"type": "BUTTERFLY", "amount": 2},
        {"type": "LEAF", "amount": 1}
      ],
      "cornersJ": [
        {"direction": "TL", "frontResource": "NULL", "backResource": "NULL"},
        {"direction": "TR", "frontResource": "QUILL", "backResource": "NULL"},
        {"direction": "BL", "frontResource": "FILLED", "backResource": "NULL"},
        {"direction": "BR", "frontResource": "NULL", "backResource": "NULL"}
      ],
      "backResource": "BUTTERFLY",
      "frontImageFileName": "img_G30_front.jpg",
      "backImageFileName": "img_G30_back.jpg"
    },
    {
      "cardId": "G31",
      "pointsOnPlace": [
        {"type": "SCROLL", "amount": 1}
      ],
      "placementCost": [
        {"type": "BUTTERFLY", "amount": 2},
        {"type": "WOLF", "amount": 1}
      ],
      "cornersJ": [
        {"direction": "TL", "frontResource": "NULL", "backResource": "NULL"},
        {"direction": "TR", "frontResource": "FILLED", "backResource": "NULL"},
        {"direction": "BL", "frontResource": "SCROLL", "backResource": "NULL"},
        {"direction": "BR", "frontResource": "NULL", "backResource": "NULL"}
      ],
      "backResource": "BUTTERFLY",
      "frontImageFileName": "img_G31_front.jpg",
      "backImageFileName": "img_G30_back.jpg"
    },
    {
      "cardId": "G32",
      "pointsOnPlace": [
        {"type": "POTION", "amount": 1}
      ],
      "placementCost": [
        {"type": "BUTTERFLY", "amount": 2},
        {"type": "MUSHROOM", "amount": 1}
      ],
      "cornersJ": [
        {"direction": "TL", "frontResource": "FILLED", "backResource": "NULL"},
        {"direction": "TR", "frontResource": "NULL", "backResource": "NULL"},
        {"direction": "BL", "frontResource": "NULL", "backResource": "NULL"},
        {"direction": "BR", "frontResource": "POTION", "backResource": "NULL"}
      ],
      "backResource": "BUTTERFLY",
      "frontImageFileName": "img_G32_front.jpg",
      "backImageFileName": "img_G30_back.jpg"
    },
    {
      "cardId": "G33",
      "pointsOnPlace": [
        {"type": "CORNERCOVER", "amount": 2}
      ],
      "placementCost": [
        {"type": "BUTTERFLY", "amount": 3},
        {"type": "WOLF", "amount": 1}
      ],
      "cornersJ": [
        {"direction": "TL", "frontResource": "NULL", "backResource": "NULL"},
        {"direction": "TR", "frontResource": "NULL", "backResource": "NULL"},
        {"direction": "BL", "frontResource": "FILLED", "backResource": "NULL"},
        {"direction": "BR", "frontResource": "NULL", "backResource": "NULL"}
      ],
      "backResource": "BUTTERFLY",
      "frontImageFileName": "img_G33_front.jpg",
      "backImageFileName": "img_G30_back.jpg"
    },
    {
      "cardId": "G34",
      "pointsOnPlace": [
        {"type": "CORNERCOVER", "amount": 2}
      ],
      "placementCost": [
        {"type": "BUTTERFLY", "amount": 3},
        {"type": "LEAF", "amount": 1}
      ],
      "cornersJ": [
        {"direction": "TL", "frontResource": "NULL", "backResource": "NULL"},
        {"direction": "TR", "frontResource": "NULL", "backResource": "NULL"},
        {"direction": "BL", "frontResource": "NULL", "backResource": "NULL"},
        {"direction": "BR", "frontResource": "FILLED", "backResource": "NULL"}
      ],
      "backResource": "BUTTERFLY",
      "frontImageFileName": "img_G34_front.jpg",
      "backImageFileName": "img_G30_back.jpg"
    },
    {
      "cardId": "G35",
      "pointsOnPlace": [
        {"type": "CORNERCOVER", "amount": 2}
      ],
      "placementCost": [
        {"type": "BUTTERFLY", "amount": 3},
        {"type": "MUSHROOM", "amount": 1}
      ],
      "cornersJ": [
        {"direction": "TL", "frontResource": "NULL", "backResource": "NULL"},
        {"direction": "TR", "frontResource": "FILLED", "backResource": "NULL"},
        {"direction": "BL", "frontResource": "NULL", "backResource": "NULL"},
        {"direction": "BR", "frontResource": "NULL", "backResource": "NULL"}
      ],
      "backResource": "BUTTERFLY",
      "frontImageFileName": "img_G35_front.jpg",
      "backImageFileName": "img_G30_back.jpg"
    },
    {
      "cardId": "G36",
      "pointsOnPlace": [
        {"type":  "SIMPLEPOINT", "amount":  3}
      ],
      "placementCost": [
        {"type": "BUTTERFLY", "amount": 3}
      ],
      "cornersJ": [
        {"direction": "TL", "frontResource": "POTION", "backResource": "NULL"},
        {"direction": "TR", "frontResource": "FILLED", "backResource": "NULL"},
        {"direction": "BL", "frontResource": "NULL", "backResource": "NULL"},
        {"direction": "BR", "frontResource": "FILLED", "backResource": "NULL"}
      ],
      "backResource": "BUTTERFLY",
      "frontImageFileName": "img_G36_front.jpg",
      "backImageFileName": "img_G30_back.jpg"
    },
    {
      "cardId": "G36",
      "pointsOnPlace": [
        {"type":  "SIMPLEPOINT", "amount":  3}
      ],
      "placementCost": [
        {"type": "BUTTERFLY", "amount": 3}
      ],
      "cornersJ": [
        {"direction": "TL", "frontResource": "NULL", "backResource": "NULL"},
        {"direction": "TR", "frontResource": "SCROLL", "backResource": "NULL"},
        {"direction": "BL", "frontResource": "FILLED", "backResource": "NULL"},
        {"direction": "BR", "frontResource": "FILLED", "backResource": "NULL"}
      ],
      "backResource": "BUTTERFLY",
      "frontImageFileName": "img_G37_front.jpg",
      "backImageFileName": "img_G30_back.jpg"
    },
    {
      "cardId": "G38",
      "pointsOnPlace": [
        {"type":  "SIMPLEPOINT", "amount":  3}
      ],
      "placementCost": [
        {"type": "BUTTERFLY", "amount": 3}
      ],
      "cornersJ": [
        {"direction": "TL", "frontResource": "FILLED", "backResource": "NULL"},
        {"direction": "TR", "frontResource": "FILLED", "backResource": "NULL"},
        {"direction": "BL", "frontResource": "QUILL", "backResource": "NULL"},
        {"direction": "BR", "frontResource": "NULL", "backResource": "NULL"}
      ],
      "backResource": "BUTTERFLY",
      "frontImageFileName": "img_G38_front.jpg",
      "backImageFileName": "img_G30_back.jpg"
    },
    {
      "cardId": "G39",
      "pointsOnPlace": [
        {"type":  "SIMPLEPOINT", "amount":  5}
      ],
      "placementCost": [
        {"type": "BUTTERFLY", "amount": 5}
      ],
      "cornersJ": [
        {"direction": "TL", "frontResource": "NULL", "backResource": "NULL"},
        {"direction": "TR", "frontResource": "NULL", "backResource": "NULL"},
        {"direction": "BL", "frontResource": "FILLED", "backResource": "NULL"},
        {"direction": "BR", "frontResource": "FILLED", "backResource": "NULL"}
      ],
      "backResource": "BUTTERFLY",
      "frontImageFileName": "img_G39_front.jpg",
      "backImageFileName": "img_G30_back.jpg"
    }
  ]
}